README
setup.py
tornadorpc/__init__.py
tornadorpc/base.py
tornadorpc/json.py
tornadorpc/utils.py
tornadorpc/xml.py
tornadorpc.egg-info/PKG-INFO
tornadorpc.egg-info/SOURCES.txt
tornadorpc.egg-info/dependency_links.txt
tornadorpc.egg-info/requires.txt
tornadorpc.egg-info/top_level.txt