Metadata-Version: 1.0
Name: tornadorpc
Version: 0.1.1
Summary: TornadoRPC is a an implementation of both JSON-RPC and XML-RPC handlers for the Tornado framework.
Home-page: http://code.google.com/p/tornadorpc/
Author: Josh Marshall
Author-email: catchjosh@gmail.com
License: http://www.apache.org/licenses/LICENSE-2.0
Platform: UNKNOWN
